ComputerNumber/Calculator.py
ComputerNumber/__init__.py
Test/TestDemo.py
Test/__init__.py
boyixingyu_computer-0.0.1.dist-info/LICENSE
boyixingyu_computer-0.0.1.dist-info/METADATA
boyixingyu_computer-0.0.1.dist-info/WHEEL
boyixingyu_computer-0.0.1.dist-info/top_level.txt
boyixingyu_computer-0.0.1.dist-info/RECORD
