Metadata-Version: 2.1
Name: boyixingyu-computer
Version: 0.0.1
Summary: 计算加减乘除
Home-page: UNKNOWN
Author: boyixingyu
Author-email: boyixingyu@163.com
License: UNKNOWN
Platform: UNKNOWN
License-File: LICENSE
